MFEGaussF/MFE_GaussF_esti.py
MFEGaussF/__init__.py
MFEGaussF/kmer_counting_loop.py
MFEGaussF/kmer_frequency_distribution_mini_shared.py
MFEGaussF/merge_normalize_isoform_count_v1.py
MFEGaussF/merge_normalized_isoform_count_TPM.py
MFEGaussF/pipeline_abundance_GaussF_esti_loop.py
MFE_GaussF-0.1.2.dist-info/LICENSE
MFE_GaussF-0.1.2.dist-info/METADATA
MFE_GaussF-0.1.2.dist-info/WHEEL
MFE_GaussF-0.1.2.dist-info/entry_points.txt
MFE_GaussF-0.1.2.dist-info/top_level.txt
MFE_GaussF-0.1.2.dist-info/RECORD
