Metadata-Version: 2.1
Name: MFE_GaussF
Version: 0.1.2
Summary: A sophisticated tool for normalizing and quantifying isoform counts from RNA-seq data
Home-page: https://github.com/QiangSu/MFEGaussF
Author: Qiang Su
Author-email: qiang_su@hotmail.com
License: MIT
Classifier: Programming Language :: Python :: 3
Classifier: License :: OSI Approved :: MIT License
Classifier: Operating System :: OS Independent
Requires-Python: >=3.6
License-File: LICENSE
